_pygraphblas.abi3.so
pygraphblas.libs/libgomp-f7e03b3e.so.1.0.0
pygraphblas.libs/libgraphblas-f50300a5.so.4.0.3
pygraphblas-4.2.2.dist-info/top_level.txt
pygraphblas-4.2.2.dist-info/RECORD
pygraphblas-4.2.2.dist-info/METADATA
pygraphblas-4.2.2.dist-info/WHEEL
pygraphblas-4.2.2.dist-info/LICENSE
pygraphblas/__init__.py
pygraphblas/vector.py
pygraphblas/scalar.py
pygraphblas/binaryop.py
pygraphblas/build.py
pygraphblas/unaryop.py
pygraphblas/descriptor.py
pygraphblas/matrix.py
pygraphblas/monoid.py
pygraphblas/types.py
pygraphblas/gviz.py
pygraphblas/selectop.py
pygraphblas/base.py
pygraphblas/semiring.py
